exp_heatmap/__init__.py
exp_heatmap/cli.py
exp_heatmap/compute.py
exp_heatmap/plot.py
exp_heatmap/prepare.py
exp_heatmap/rank_tools.py
exp_heatmap/tests.py
exp_heatmap/utils.py
exp_heatmap/xp_utils.py
exp_heatmap-1.1.5.dist-info/licenses/LICENSE
exp_heatmap-1.1.5.dist-info/METADATA
exp_heatmap-1.1.5.dist-info/WHEEL
exp_heatmap-1.1.5.dist-info/entry_points.txt
exp_heatmap-1.1.5.dist-info/top_level.txt
exp_heatmap-1.1.5.dist-info/RECORD
