Metadata-Version: 2.4
Name: exp_heatmap
Version: 1.1.5
Summary: Computing and drawing ExP heatmap for displaying complex cross-population data
Author: Ondřej Moravčík
Author-email: Edvard Ehler <edvard.ehler@img.cas.cz>
Maintainer-email: Adam Nógell <adam.nogell@img.cas.cz>
Project-URL: Homepage, https://github.com/bioinfocz/exp_heatmap
Project-URL: Bug Tracker, https://github.com/bioinfocz/exp_heatmap/issues
Classifier: Programming Language :: Python :: 3
Classifier: License :: OSI Approved :: MIT License
Classifier: Operating System :: OS Independent
Classifier: Topic :: Scientific/Engineering :: Bio-Informatics
Requires-Python: >=3.8
License-File: LICENSE
Requires-Dist: scikit-allel
Requires-Dist: zarr<3.0.0
Requires-Dist: numpy
Requires-Dist: pandas
Requires-Dist: matplotlib
Requires-Dist: seaborn
Requires-Dist: click
Dynamic: license-file
